mechanix/__init__.py
mechanix/_base_client.py
mechanix/_client.py
mechanix/_compat.py
mechanix/_constants.py
mechanix/_exceptions.py
mechanix/_files.py
mechanix/_models.py
mechanix/_qs.py
mechanix/_resource.py
mechanix/_response.py
mechanix/_streaming.py
mechanix/_types.py
mechanix/_version.py
mechanix/py.typed
mechanix/_utils/__init__.py
mechanix/_utils/_logs.py
mechanix/_utils/_proxy.py
mechanix/_utils/_reflection.py
mechanix/_utils/_streams.py
mechanix/_utils/_sync.py
mechanix/_utils/_transform.py
mechanix/_utils/_typing.py
mechanix/_utils/_utils.py
mechanix/lib/.keep
mechanix/resources/__init__.py
mechanix/resources/health.py
mechanix/resources/root.py
mechanix/resources/tools.py
mechanix/resources/users.py
mechanix/types/__init__.py
mechanix/types/tool_search_web_params.py
mechanix/types/tool_search_web_response.py
mechanix/types/tool_summarize_content_params.py
mechanix/types/tool_summarize_content_response.py
mechanix/types/user_model.py
mechanix/types/user_view_params.py
mechanix-0.1.0a6.dist-info/METADATA
mechanix-0.1.0a6.dist-info/WHEEL
mechanix-0.1.0a6.dist-info/licenses/LICENSE
mechanix-0.1.0a6.dist-info/RECORD
